eonconsoleui/__init__.py
guiphyton-1.0.0.dist-info/METADATA
guiphyton-1.0.0.dist-info/WHEEL
guiphyton-1.0.0.dist-info/top_level.txt
guiphyton-1.0.0.dist-info/RECORD
