Metadata-Version: 2.4
Name: guiphyton
Version: 1.0.0
Summary: A fully custom console UI toolkit without tkinter or graphics!
Author: Ruzgar
Author-email: ruzgartvtr@gmail.com
Classifier: Programming Language :: Python :: 3
Classifier: Operating System :: OS Independent
Requires-Python: >=3.6
Dynamic: author
Dynamic: author-email
Dynamic: classifier
Dynamic: description
Dynamic: description-content-type
Dynamic: requires-python
Dynamic: summary
